<?xml version="1.0" encoding="utf-8"?>
<ModPlus>
  <mprParameters
    LocalName="参数"
    Description="批量编辑/添加项目及族参数"
    LocalName1="族编辑器"
    Description1="标准族参数编辑器的替代工具，支持使用公式编辑器">
    <pcn1>在项目中创建参数</pcn1>
    <pcd1>批量在当前项目中创建参数</pcd1>
    <pcn2>在族中创建参数</pcn2>
    <pcd2>批量在项目族、已打开族或磁盘上的族文件中创建参数</pcd2>
    <!-- todo remove after 1.6.2.0 -->
    <pcn3>族编辑器</pcn3>
    <!-- todo remove after 1.6.2.0 -->
    <pcd3>标准族参数编辑器的替代工具，支持使用公式编辑器</pcd3>
    <pcn4>编辑项目参数</pcn4>
    <pcd4>批量编辑当前项目中的参数</pcd4>
    <pcn5>编辑族参数</pcn5>
    <pcd5>批量编辑项目族、已打开族或磁盘上的族文件中的参数</pcd5>
    <t1>无文档</t1>
    <t2>族</t2>
    <t3>项目</t3>
    <t4>正在根据族 {0} 验证公式</t4>
    <t5>公式编辑器基于族 {0} 的数据打开。未执行公式验证</t5>
    <t6>正在关闭族 {0}</t6>
    <t7>包含参数"{0}"的族</t7>
    <t8>选择参数</t8>
    <t9>修改公式</t9>
    <t10>修改参数组</t10>
    <t11>修改行为</t11>
    <t12>按实例组的值可以变化</t12>
    <t13>按类型组的值对齐</t13>
    <!--todo remove after 1.6.2.0-->
    <t14>设为"按实例"</t14>
    <!--todo remove after 1.6.2.0-->
    <t15>设为"按类型"</t15>
    <t16>重命名</t16>
    <t17>参数已存在于当前文档中</t17>
    <t18>新建参数</t18>
    <t19>按实例</t19>
    <t20>共享参数</t20>
    <t21>内置参数</t21>
    <t22>族参数</t22>
    <t23>族</t23>
    <t24>*不同*</t24>
    <t25>未定义数据类型</t25>
    <t26>项目参数</t26>
    <t27>按类型</t27>
    <t28>验证参数属性</t28>
    <t29>其他</t29>
    <t30>按FOP分组</t30>
    <t31>数据类型</t31>
    <t32>参数分组</t32>
    <t33>处理族</t33>
    <t34>添加参数</t34>
    <t35>正在设置参数值...</t35>
    <t36>正在设置公式值...</t36>
    <t37>添加参数</t37>
    <t38>参数已创建</t38>
    <t39>参数已更新</t39>
    <t40>跳过参数更新</t40>
    <t41>输入新名称</t41>
    <t42>选择新分组</t42>
    <t43>输入类型名称</t43>
    <t44>处理参数</t44>
    <t45>读取族</t45>
    <t46>获取参数数据</t46>
    <t47>批量编辑参数</t47>
    <t48>更新项目参数</t48>
    <t49>创建项目参数</t49>
    <t50>设置默认值</t50>
    <t51>名称</t51>
    <t52>实例/类型</t52>
    <t53>按组的值</t53>
    <t54>默认值</t54>
    <t55>类别</t55>
    <t56>项目参数</t56>
    <t57>族参数</t57>
    <t58>选择文件保存路径</t58>
    <t59>修改当前类型</t59>
    <t60>创建类型</t60>
    <t61>删除类型</t61>
    <t62>重命名类型</t62>
    <t63>删除参数</t63>
    <t64>替换参数</t64>
    <t65>设置公式</t65>
    <t66>设置参数值</t66>
    <t67>修改参数锁定状态</t67>
    <t68>修改"实例/类型"属性</t68>
    <t69>创建参数</t69>
    <t70>自定义参数</t70>
    <t71>共享参数文件</t71>
    <t72>导出到Excel后的操作：</t72>
    <t73>参数已存在时的操作：</t73>
    <t74>获取数据</t74>
    <t75>从文件</t75>
    <t76>从文件夹</t76>
    <t77>待处理族</t77>
    <t78>清空列表中的所有族</t78>
    <t79>插入参数</t79>
    <t80>插入函数</t80>
    <t81>全选/取消全选</t81>
    <t82>选择FOP：</t82>
    <t83>当前FOP</t83>
    <t84>已选FOP</t84>
    <t85>FOP路径：</t85>
    <!--todo remove after 1.6.2.0-->
    <t86>从FOP添加</t86>
    <t87>将FOP中选定的参数添加到当前参数列表</t87>
    <t88>组</t88>
    <t89>参数定义</t89>
    <t90>参数总数：</t90>
    <t91>已选参数：</t91>
    <t92>创建族参数</t92>
    <t93>导出参数列表到Excel</t93>
    <t94>从Excel导入参数列表</t94>
    <t95>删除列表中选定的参数</t95>
    <t96>清空列表中的所有参数</t96>
    <t97>创建</t97>
    <!--todo remove after 1.6.2.0-->
    <t98>实例</t98>
    <!--todo remove after 1.6.2.0-->
    <t99>类型</t99>
    <t100>公式编辑器</t100>
    <t101>执行并关闭</t101>
    <t102>编辑选定参数的类别列表</t102>
    <t103>创建自定义参数。自定义参数将作为不带FOP绑定的共享参数（随机GUID）</t103>
    <t104>状态</t104>
    <t105>不支持</t105>
    <t106>类型名称：</t106>
    <t107>新建类型</t107>
    <t108>删除当前类型</t108>
    <t109>将共享参数替换为族参数</t109>
    <t110>锁定</t110>
    <t111>不可用</t111>
    <t112>设为实例参数</t112>
    <t113>设为类型参数</t113>
    <t114>清空操作列表</t114>
    <t115>数量</t115>
    <t116>包含该参数的族数量</t116>
    <t117>操作</t117>
    <t118>按组修改</t118>
    <t119>按实例修改</t119>
    <!-- todo remove after 1.6.2.0 -->
    <t120>按组的值</t120>
    <t121>验证</t121>
    <t122>不验证直接应用</t122>
    <t123>将当前公式添加到收藏列表</t123>
    <t124>从收藏列表插入公式</t124>
    <t125>章节</t125>
    <t126>当前文档类型：</t126>
    <t127>可用章节：</t127>
    <t128>不可用章节：</t128>
    <t129>{0}个类别</t129>
    <t130>试用期剩余天数</t130>
    <t131>插件试用期已结束！请购买插件许可证或Revit订阅以继续使用"参数"插件</t131>
    <t132>收藏的公式</t132>
    <t133>忽略嵌套族</t133>
    <t134>其他</t134>
    <t135>在族文档中启动插件时打开章节：</t135>
    <t136>在数据类型列表、参数组、列筛选器及从FOP添加参数时区分大小写</t136>
    <!-- todo remove after 1.6.2.0 -->
    <t137>修改组</t137>
    <t138>为参数"{0}"选择新分组</t138>
    <t139>选择族</t139>
    <t140>删除备份文件</t140>
    <t141>保存族后，将删除族文件所在目录中所有名为"族名称.nnnn.rfa"的备份文件</t141>
    <t142>由于Revit API限制，修改非共享族参数的组时将丢失描述！</t142>
    <t143>当前族类型不支持使用插件。族编辑器处于"只读"模式</t143>
    <t144>导入文件中未找到与参数对应的行</t144>
    <t145>无法识别"{0}"中的操作。请确保应用语言与导入文件匹配</t145>
    <t146>已识别"{0}"中的操作，但未添加到参数"{1}"（操作不适用或参数已标记为删除）</t146>
    <t147>无法识别"{0}"中指定的组。某些组名可能因Revit版本而异</t147>
    <t148>您没有权限将预设保存到组织存储库</t148>
    <t149>加载预设</t149>
    <t150>保存预设</t150>
    <t151>预设名称</t151>
    <t152>存储库中没有当前章节的预设</t152>
    <t153>修改参数定义</t153>
    <t154>添加类别</t154>
    <t155>删除类别</t155>
    <t156>为选定参数添加操作</t156>
    <t157>选择操作</t157>
    <t158>未绑定到项目类别</t158>
    <t159>修改类别绑定</t159>
    <t160>保存到：</t160>
    <t161>用户存储库</t161>
    <t162>组织存储库</t162>
    <t163>删除未使用的参数</t163>
    <t164>删除标记的参数</t164>
    <t165>已使用</t165>
    <t166>无法删除内置参数</t166>
    <t167>在参数"{0}"的公式中使用</t167>
    <t168>在尺寸(ID={0})中使用</t168>
    <t169>在阵列(ID={0})中使用</t169>
    <t170>与元素ID={1}的参数"{0}"关联</t170>
    <t171>提示</t171>
    <t172>设置提示</t172>
    <t173>Revit API无法获取参数的现有提示</t173>
    <t174>将族参数替换为共享参数</t174>
    <t175>选择参数</t175>
    <t176>将共享参数替换为其他共享参数</t176>
    <t177>复制参数</t177>
    <t178>调整参数顺序</t178>
    <t179>拖动表格中的参数以重新排序（支持多选及跨组拖动）</t179>
    <t180>由于Revit API限制，系统参数不能移动到其他组</t180>
    <t181>族文件</t181>
    <t182>从选定族导入参数</t182>
    <t183>导入参数</t183>
    <t184>导入参数数量</t184>
    <t185>当前族</t185>
    <t186>选定族</t186>
    <t187>通过创建具有选定族参数特性的参数并设置值和公式来导入参数。选择带公式的参数时，公式中使用的所有参数将被添加到列表。无法导入系统参数。左侧需选择当前族与选定族的类型对应关系以复制参数值</t187>
    <t188>由于Revit API限制，导入参数时会丢失描述（除非选定的共享参数存在于当前共享参数文件中）</t188>
    <t189>导入公式</t189>
    <t190>从选定族的参数导入公式</t190>
    <t191>选定族中没有带公式的参数</t191>
    <t192>锁定</t192>
    <t193>解锁</t193>
    <t194>替换为参数</t194>
    <t195>替换为共享参数</t195>
    <t196>按名称或GUID搜索</t196>
    <t197>按名称、GUID或类别搜索</t197>
    <t198>导入选择表</t198>
    <t199>用不同公式对相同参数进行分组</t199>
    <t200>所有参数定义</t200>
    <t201>报告参数</t201>
    <ad1>允许重命名族参数（不适用于系统参数和共享参数）</ad1>
    <ad2>允许修改参数组（不适用于系统参数。修改非共享族参数的组时将丢失描述）</ad2>
    <ad3>允许修改参数组（不适用于项目参数）</ad3>
    <ad4>允许添加/删除共享参数的类别绑定（不适用于项目参数。删除绑定时将移除该类别下所有元素的参数数据）</ad4>
    <ad6>允许将族参数设为实例参数（不适用于系统参数）</ad6>
    <ad7>允许将共享参数设为实例参数（不适用于项目参数）</ad7>
    <ad8>允许将族参数设为类型参数（不适用于系统参数）</ad8>
    <ad9>允许将共享参数设为类型参数（不适用于项目参数）</ad9>
    <ad10>允许设置"按实例组的值可以变化"行为</ad10>
    <ad11>允许设置"按类型组的值对齐"行为</ad11>
    <ad12>允许删除参数（不适用于系统参数）</ad12>
    <ad13>允许删除参数</ad13>
    <ad14>允许将共享参数替换为同名族参数</ad14>
    <ad15>允许启用参数的"锁定"属性</ad15>
    <ad16>允许禁用参数的"锁定"属性</ad16>
    <ad17>允许将族参数/共享参数替换为同数据类型的其他共享参数（保留公式和标签）</ad17>
    <ea1>无操作</ea1>
    <ea2>打开目标文件夹</ea2>
    <ea3>打开生成的文件</ea3>
    <ea4>询问是否打开目标文件夹</ea4>
    <ep1>跳过</ep1>
    <ep2>设置公式（如可能）</ep2>
    <ep3>设置值（如可能）</ep3>
    <ep4>设置公式或值（如可能）</ep4>
    <fs1>从文件</fs1>
    <fs2>从项目</fs2>
    <fs3>已打开的族</fs3>
    <fs4>从项目管理器</fs4>
    <s1>选定元素</s1>
    <s2>在当前视图</s2>
    <s3>在整个项目</s3>
    <d1>常规</d1>
    <d2>电气</d2>
    <d3>能量</d3>
    <d4>暖通</d4>
    <d5>管道</d5>
    <d6>结构</d6>
    <d7>基础设施</d7>
    <spf1>在共享参数文件中未找到该参数</spf1>
    <spf2>在共享参数文件中找到该参数</spf2>
    <spf3>共享参数文件中存在同名但GUID不同的参数</spf3>
    <spf4>共享参数文件中存在同GUID但名称不同的参数</spf4>
    <spf5>未指定共享参数文件，无法搜索参数</spf5>
    <msg1>公式已添加到收藏列表</msg1>
    <msg2>当前公式非空，确认替换为收藏列表中的公式？</msg2>
    <msg3>共享参数已存在于当前参数列表</msg3>
    <msg4>同名、同数据类型且同分组的参数已存在</msg4>
    <msg5>无法重命名所有选定参数</msg5>
    <msg6>类型"{0}"已存在</msg6>
    <msg7>确认删除类型"{0}"？</msg7>
    <msg8>删除参数"{0}"？</msg8>
    <msg9>删除选定的{0}个参数？</msg9>
    <msg10>跳过创建参数（族中已存在该参数）</msg10>
    <msg12>参数未创建</msg12>
    <msg13>参数值已设置</msg13>
    <msg14>设置参数值失败</msg14>
    <msg15>参数公式已更新</msg15>
    <msg16>更新参数公式失败</msg16>
    <msg17>参数已删除</msg17>
    <msg18>参数已重命名</msg18>
    <msg19>值"{0}"已设置</msg19>
    <msg20>未知操作</msg20>
    <msg21>参数"{0}"已删除</msg21>
    <msg22>公式已修改</msg22>
    <msg23>参数已设为"按实例"</msg23>
    <msg24>参数已设为"按类型"</msg24>
    <msg25>参数已移动到"{0}"组</msg25>
    <msg26>是否打开导出文件夹？</msg26>
    <msg27>是否处理子文件夹中的族文件？</msg27>
    <msg28>公式编辑器将在不验证公式的情况下打开</msg28>
    <msg29>当前项目未指定共享参数文件</msg29>
    <!--todo remove after 1.6.2.0-->
    <msg30>请检查参数名称和类型是否填写完整</msg30>
    <msg31>请检查参数名称、类型、分组及类别列表是否填写完整</msg31>
    <msg32>输入值与参数类型不匹配</msg32>
    <msg33>Revit API不支持某些族类型的参数创建/编辑。已跳过加载这些族</msg33>
    <msg34>预设"{0}"将被永久删除！继续？</msg34>
    <msg35>预设"{0}"已删除</msg35>
    <msg36>共享参数已替换为族参数</msg36>
    <msg37>参数已绑定到以下类别：</msg37>
    <msg38>参数已解除绑定的类别：</msg38>
    <msg39>插件仅在族文档中可用！</msg39>
    <msg40>参数的"锁定"属性已启用</msg40>
    <msg41>参数的"锁定"属性已禁用</msg41>
    <msg42>请选择数据类型相同的参数</msg42>
    <msg43>参数已替换</msg43>
    <msg44>仅可在已保存的族中导入参数！请保存当前族后重试</msg44>
    <msg45>导入参数"{0}"的名称与当前共享参数文件中同GUID参数不一致。已采用共享参数文件中的名称</msg45>
    <err1>窗口初始化时发生意外错误</err1>
    <err2>窗口关闭时发生意外错误</err2>
    <err3>创建参数时出错</err3>
    <err4>添加参数绑定失败</err4>
    <err5>获取参数绑定失败</err5>
    <err6>更新参数绑定失败</err6>
    <err7>执行操作失败</err7>
    <err8>对参数"{0}"执行操作失败</err8>
    <err9>跳过GUID为"{0}"的参数（未指定FOP）</err9>
    <err10>在当前FOP中未找到GUID为"{0}"的参数</err10>
    <err11>无法识别参数的数据类型"{0}"</err11>
    <err12>无法识别参数的分组"{0}"</err12>
    <err13>无法识别参数"{0}"的类别</err13>
    <err14>读取行失败</err14>
    <err15>族文件为更高版本的Revit创建</err15>
    <err16>无法将值"{0}"赋给整数型参数</err16>
    <err17>不支持的数据类型"{0}"</err17>
    <err18>实例参数不能用于类型参数的公式</err18>
    <err19>设置公式失败</err19>
    <err20>无法在族"{1}"中创建参数"{0}"</err20>
    <err21>族文件为只读属性，未加载</err21>
    <err22>由于Revit API未控错误（可能是API漏洞），无法设置公式。请使用标准参数编辑器</err22>
    <err23>请输入预设名称</err23>
    <err24>存储库中已存在同名预设。将覆盖现有预设！</err24>
    <err25>预设名称不能包含以下字符：\ / : * ? " &lt; &gt; |</err25>
    <err26>缺少预设存储目录！请检查UserData目录的读写权限或联系系统管理员</err26>
    <err27>执行操作失败</err27>
    <err28>参数"{0}"已存在。请使用其他名称</err28>
    <err29>选定族为当前族。请选择其他族</err29>
    <err30>导入参数失败。错误：</err30>
    <err31>设置公式失败。错误：</err31>
    <err32>无法导入参数值</err32>
    <err33>无法撤销更改（当前文档非族编辑文档）。请手动切换至族文档撤销</err33>
    <err34>"图像"类型参数不能是实例参数</err34>
    <err35>未指定参数名称</err35>
    <err36>未指定参数数据类型</err36>
    <err37>未指定参数绑定类别</err37>
    <err38>未指定参数分组</err38>
    <err39>族"{0}"已存在同名参数"{1}"，无法替换</err39>
    <err40>导入选择表"{0}"失败。错误：</err40>
    <err41>文件"{0}"未找到</err41>
    <err42>读取文件"{0}"失败</err42>
    <err43>打开文件"{0}"失败</err43>
    <err44>无效的标题分隔符</err44>
    <err45>无法识别第{0}列的标题</err45>
    <err46>列数不正确</err46>
    <err47>未知错误</err47>
    <err48>当前族中无法创建选择表</err48>
    <err49>无法修改类别绑定：不能移除所有绑定类别</err49>
    <err50>无法启用"报告参数"选项。错误:</err50>
    <err51>"报告参数"选项仅适用于使用以下数据类型创建的实例参数:</err51>
  </mprParameters>
</ModPlus>