<?xml version="1.0" encoding="utf-8"?>
<ModPlus>
  <mncMultiMirror LocalName="Multiespejo" Description="Complemento le permite reflejar cada uno de objetos seleccionados vertical u horizontalmente con respecto a ellos mismos" FullDescription="Cada objeto seleccionado se volteará vertical u horizontalmente en relación con línea que pasa por punto especificado: Abajo a izquierda, Abajo a derecha, Arriba a izquierda, Arriba a derecha o Centro. Punto está determinado por rectángulo que describe objeto">
    <o1>Reflejar</o1>
    <o2>verticalmente</o2>
    <o3>horizontalmente</o3>
  </mncMultiMirror>
</ModPlus>