<?xml version="1.0" encoding="utf-8"?>
<ModPlus>
  <mncDrawOrderByLayer LocalName="Порядок по шару" Description="Плагін служить для зміни порядку промальовування згідно слоїв" FullDescription="Плагін обробляє слої, відмічені у вікні прапорцями, змінюючи порядок промальовування згідно з порядком відмічених слоїв. Присутній режим &quot;Авто&quot;, який автоматично змінює порядок промальовування об'єктів на одному з двох зазначених шарів при створенні або редагуванні">
    <h2>Реверс списку</h2>
    <h5>Інверсія вибору</h5>
    <h6>Режим "Авто"</h6>
    <h7>На передній план</h7>
    <h8>На задній план</h8>
    <h9>Застосувати</h9>
    <h10>ModPlus: Об'єкт на слої:</h10>
    <h11>переміщено на передній план</h11>
    <h12>переміщений на задній план</h12>
    <h13>Зберегти поточне положення слоїв у кресленні</h13>
    <h14>Завантажити та застосувати збережене в поточному кресленні положення слоїв. Слої, які були додані після збереження положення, будуть переміщені в кінець списку</h14>
    <h15>Перемістити вибраний шар на початок списку</h15>
  </mncDrawOrderByLayer>
</ModPlus>