<?xml version="1.0" encoding="utf-8"?>
<ModPlus>
  <mprVisibility
    LocalName="Visibility"
    Description="Control visibility of various objects and elements on selected views">
    <t2>Linked files</t2>
    <t3>DWG imports</t3>
    <t4>Point clouds</t4>
    <t5>Worksets</t5>
    <t6>Hide elements on views</t6>
    <t7>Show elements on views</t7>
    <t8>Hide categories on views</t8>
    <t9>Show categories on views</t9>
    <t10>Hide links on views</t10>
    <t11>Show links on views</t11>
    <t12>Hide DWG imports on views</t12>
    <t13>Show DWG imports on views</t13>
    <t14>Hide point clouds on views</t14>
    <t15>Show point clouds on views</t15>
    <t16>Hide worksets on views</t16>
    <t17>Show worksets on views</t17>
    <t18>Change categories visibility</t18>
    <t19>Change links visibility</t19>
    <t20>Change DWG imports visibility</t20>
    <t21>Change worksets visibility</t21>
    <t22>Change point clouds visibility</t22>
    <t23>Visibility of category "{0}" cannot be changed on the view</t23>
    <t24>Model categories</t24>
    <t25>Annotation categories</t25>
    <t26>Analytical model categories</t26>
    <t27>A template is applied to the current view. Links visibility will be changed in the template</t27>
    <t28>A template is applied to the current view. DWG imports visibility will be changed in the template</t28>
    <t29>A template is applied to the current view. Point clouds visibility will be changed in the template</t29>
    <t30>A template is applied to the current view. Worksets visibility will be changed in the template</t30>
    <t31>Model categories are defined by the view template. Categories visibility will be changed in the template</t31>
    <t32>Annotation categories are defined by the view template. Categories visibility will be changed in the template</t32>
    <t33>Analytical model categories are defined by the view template. Categories visibility will be changed in the template</t33>
    <t34>Scan Locations</t34>
    <t35>Scan Regions</t35>
    <t36>Visible on the current view</t36>
    <t37>Hidden on the current view</t37>
    <t38>Global setting is used</t38>
    <t39>There are no linked files in the current document</t39>
    <t40>There are no DWG imports in the current document</t40>
    <t41>There are no point clouds in the current document</t41>
    <t42>The current document is not workshared</t42>
    <t43>Hide on views</t43>
    <t44>Show on views</t44>
    <t45>Selected elements</t45>
    <t46>Select section</t46>
    <t47>Refresh data</t47>
  </mprVisibility>
</ModPlus>